opentabulate/__init__.py
opentabulate/main/__init__.py
opentabulate/main/algorithm.py
opentabulate/main/args.py
opentabulate/main/cache.py
opentabulate/main/config.py
opentabulate/main/main.py
opentabulate/main/main_funcs.py
opentabulate/main/source.py
opentabulate/main/tabulate.py
opentabulate/main/thread.py
opentabulate/main/thread_exception.py
opentabulate/share/opentabulate.conf.example
opentabulate/tests/__init__.py
opentabulate/tests/test_algorithm.py
opentabulate/tests/data/.gitignore
opentabulate/tests/data/csv-data.csv
opentabulate/tests/data/csv-source.json
opentabulate/tests/data/csv-target-output.csv
opentabulate/tests/data/csv-test-output.csv
opentabulate/tests/data/opentabulate.conf
opentabulate/tests/data/xml-data.xml
opentabulate/tests/data/xml-source.json
opentabulate/tests/data/xml-target-output.csv
opentabulate/tests/data/xml-test-output.csv
opentabulate-2.1.1.dist-info/LICENSE.md
opentabulate-2.1.1.dist-info/METADATA
opentabulate-2.1.1.dist-info/WHEEL
opentabulate-2.1.1.dist-info/entry_points.txt
opentabulate-2.1.1.dist-info/top_level.txt
opentabulate-2.1.1.dist-info/RECORD
