Metadata-Version: 2.1
Name: opentabulate
Version: 2.1.1
Summary: Tabulates structured data into a mergeable CSV format
Home-page: https://github.com/CSBP-CPSE/OpenTabulate
Author: Maksym Neyra-Nesterenko
License: MIT
Project-URL: Documentation, https://opentabulate.readthedocs.io/en/stable/
Project-URL: Source code, https://github.com/CSBP-CPSE/OpenTabulate/tree/master/opentabulate
Project-URL: Bug tracker, https://github.com/CSBP-CPSE/OpenTabulate/issues
Project-URL: License, https://github.com/CSBP-CPSE/OpenTabulate/tree/master/LICENSE.md
Platform: UNKNOWN
Classifier: License :: OSI Approved :: MIT License
Classifier: Topic :: Text Processing :: General
Classifier: Topic :: Utilities
Classifier: Operating System :: POSIX :: Linux
Classifier: Environment :: Console
Classifier: Programming Language :: Python :: 3.5
Classifier: Programming Language :: Python :: 3.6
Classifier: Programming Language :: Python :: 3.7
Classifier: Programming Language :: Python :: 3.8
Requires-Python: >=3.5
